Metadata-Version: 2.1
Name: lin_reg87
Version: 1.0.0
Summary: An awesome package that does something
Home-page: http://pypi.python.org/pypi/<lin_reg87>/
Author: <DAIT DEHANE YACINE>
Author-email: <y.daitdehane@esi-sba.dz>
License: LICENSE.txt
License-File: LICENSE.txt
Requires-Dist: lin_reg87
